ezmse/__init__.py
ezmse/config.py
ezmse/file.py
ezmse/include/config.ini
ezmse/include/custom-image-script-jpg
ezmse/include/custom-image-script-png
ezmse/include/set.mse-set
ezmse-0.1.2.dist-info/LICENSE
ezmse-0.1.2.dist-info/METADATA
ezmse-0.1.2.dist-info/WHEEL
ezmse-0.1.2.dist-info/top_level.txt
ezmse-0.1.2.dist-info/RECORD
