Metadata-Version: 2.1
Name: ezmse
Version: 0.1.2
Summary: A Python package for generating custom Magic: The Gathering cards
Home-page: https://github.com/TomTkacz/EasyMSE
Author: Tom Tkacz
Author-email: thomasatkacz@gmail.com
License-File: LICENSE
Requires-Dist: pyfakefs >=5.2
Provides-Extra: dev
Requires-Dist: pytest >=7.4 ; extra == 'dev'
